<annotation>
	<folder></folder>
	<filename>g20_jpg.rf.061a89a5953bc9e63d03024359e8da66.jpg</filename>
	<path>g20_jpg.rf.061a89a5953bc9e63d03024359e8da66.jpg</path>
	<source>
		<database>roboflow.ai</database>
	</source>
	<size>
		<width>640</width>
		<height>640</height>
		<depth>3</depth>
	</size>
	<segmented>0</segmented>
	<object>
		<name>glass-bottle</name>
		<pose>Unspecified</pose>
		<truncated>0</truncated>
		<difficult>0</difficult>
		<occluded>0</occluded>
		<bndbox>
			<xmin>145</xmin>
			<xmax>331</xmax>
			<ymin>16</ymin>
			<ymax>616</ymax>
		</bndbox>
	</object>
</annotation>
