<annotation>
	<folder></folder>
	<filename>IMG_20240611_023228_jpg.rf.af0fed827812b4b551c281e4a3596a35.jpg</filename>
	<path>IMG_20240611_023228_jpg.rf.af0fed827812b4b551c281e4a3596a35.jpg</path>
	<source>
		<database>roboflow.com</database>
	</source>
	<size>
		<width>640</width>
		<height>640</height>
		<depth>3</depth>
	</size>
	<segmented>0</segmented>
	<object>
		<name>air gelas</name>
		<pose>Unspecified</pose>
		<truncated>0</truncated>
		<difficult>0</difficult>
		<occluded>0</occluded>
		<bndbox>
			<xmin>21</xmin>
			<xmax>307</xmax>
			<ymin>319</ymin>
			<ymax>438</ymax>
		</bndbox>
	</object>
	<object>
		<name>air gelas</name>
		<pose>Unspecified</pose>
		<truncated>0</truncated>
		<difficult>0</difficult>
		<occluded>0</occluded>
		<bndbox>
			<xmin>336</xmin>
			<xmax>564</xmax>
			<ymin>285</ymin>
			<ymax>447</ymax>
		</bndbox>
	</object>
</annotation>
